simplejrpc/__init__.py
simplejrpc/_field.py
simplejrpc/_json.py
simplejrpc/_mapping.py
simplejrpc/_sockets.py
simplejrpc/_text.py
simplejrpc/_types.py
simplejrpc/_warnings.py
simplejrpc/app.py
simplejrpc/client.py
simplejrpc/config.py
simplejrpc/exceptions.py
simplejrpc/field.py
simplejrpc/form.py
simplejrpc/func.py
simplejrpc/i18n.py
simplejrpc/interfaces.py
simplejrpc/parse.py
simplejrpc/py.typed
simplejrpc/response.py
simplejrpc/validate.py
simplejrpc/daemon/__init__.py
simplejrpc/daemon/daemon.py
simplejrpc/daemon/exceptions.py
simplejrpc-2.2.9.dist-info/licenses/LICENSE.txt
simplejrpc-2.2.9.dist-info/METADATA
simplejrpc-2.2.9.dist-info/WHEEL
simplejrpc-2.2.9.dist-info/top_level.txt
simplejrpc-2.2.9.dist-info/RECORD
